Metadata-Version: 1.1
Name: mozsvc
Version: 0.10
Summary: Various utilities for Mozilla apps
Home-page: https://github.com/mozilla-services/mozservices
Author: Mozilla Services
Author-email: services-dev@mozilla.org
License: UNKNOWN
Keywords: web pyramid pylons
Platform: UNKNOWN
Classifier: Programming Language :: Python
Classifier: Framework :: Pylons
Classifier: Topic :: Internet :: WWW/HTTP
Classifier: Topic :: Internet :: WWW/HTTP :: WSGI :: Application
